pulsectl_asyncio/__init__.py
pulsectl_asyncio/pa_asyncio_mainloop.py
pulsectl_asyncio/pulsectl_async.py
pulsectl_asyncio-1.2.2.dist-info/LICENSE
pulsectl_asyncio-1.2.2.dist-info/METADATA
pulsectl_asyncio-1.2.2.dist-info/WHEEL
pulsectl_asyncio-1.2.2.dist-info/top_level.txt
pulsectl_asyncio-1.2.2.dist-info/RECORD
