Metadata-Version: 2.1
Name: pulsectl-asyncio
Version: 1.2.2
Summary: Asyncio frontend for the pulsectl Python bindings of libpulse
Home-page: https://github.com/mhthies/pulsectl-asyncio
Author: Michael Thies
Author-email: mail@mhthies.de
License: MIT License
Classifier: Programming Language :: Python :: 3
Classifier: Programming Language :: Python :: 3.6
Classifier: Programming Language :: Python :: 3.7
Classifier: Programming Language :: Python :: 3.8
Classifier: Programming Language :: Python :: 3.9
Classifier: Programming Language :: Python :: 3.10
Classifier: Programming Language :: Python :: 3.11
Classifier: Programming Language :: Python :: 3.12
Classifier: License :: OSI Approved :: MIT License
Classifier: Framework :: AsyncIO
Classifier: Topic :: Multimedia :: Sound/Audio :: Mixers
Classifier: Operating System :: POSIX
Classifier: Development Status :: 5 - Production/Stable
Requires-Python: >=3.6
License-File: LICENSE
Requires-Dist: pulsectl<=24.11.0,>=23.5.0
